MANIFEST.in
README.rst
setup.py
collective/.DS_Store
collective/__init__.py
collective/__init__.pyc
collective.ptg.galleryfolder.egg-info/PKG-INFO
collective.ptg.galleryfolder.egg-info/SOURCES.txt
collective.ptg.galleryfolder.egg-info/dependency_links.txt
collective.ptg.galleryfolder.egg-info/entry_points.txt
collective.ptg.galleryfolder.egg-info/namespace_packages.txt
collective.ptg.galleryfolder.egg-info/not-zip-safe
collective.ptg.galleryfolder.egg-info/requires.txt
collective.ptg.galleryfolder.egg-info/top_level.txt
collective/ptg/.DS_Store
collective/ptg/__init__.py
collective/ptg/__init__.pyc
collective/ptg/galleryfolder/.DS_Store
collective/ptg/galleryfolder/__init__.py
collective/ptg/galleryfolder/__init__.pyc
collective/ptg/galleryfolder/config.py
collective/ptg/galleryfolder/config.pyc
collective/ptg/galleryfolder/configure.zcml
collective/ptg/galleryfolder/browser/.DS_Store
collective/ptg/galleryfolder/browser/__init__.py
collective/ptg/galleryfolder/browser/__init__.pyc
collective/ptg/galleryfolder/browser/configure.zcml
collective/ptg/galleryfolder/browser/galleryexport.py
collective/ptg/galleryfolder/browser/galleryexport.pyc
collective/ptg/galleryfolder/browser/galleryicon.gif
collective/ptg/galleryfolder/browser/galleryinfo.pt
collective/ptg/galleryfolder/browser/viewlets.py
collective/ptg/galleryfolder/browser/viewlets.pyc
collective/ptg/galleryfolder/content/.DS_Store
collective/ptg/galleryfolder/content/__init__.py
collective/ptg/galleryfolder/content/__init__.pyc
collective/ptg/galleryfolder/content/configure.zcml
collective/ptg/galleryfolder/content/galleryfolder.py
collective/ptg/galleryfolder/content/galleryfolder.pyc
collective/ptg/galleryfolder/interfaces/.DS_Store
collective/ptg/galleryfolder/interfaces/__init__.py
collective/ptg/galleryfolder/interfaces/__init__.pyc
collective/ptg/galleryfolder/interfaces/galleryfolder.py
collective/ptg/galleryfolder/interfaces/galleryfolder.pyc
collective/ptg/galleryfolder/profiles/.DS_Store
collective/ptg/galleryfolder/profiles/default/.DS_Store
collective/ptg/galleryfolder/profiles/default/factorytool.xml
collective/ptg/galleryfolder/profiles/default/metadata.xml
collective/ptg/galleryfolder/profiles/default/rolemap.xml
collective/ptg/galleryfolder/profiles/default/types.xml
collective/ptg/galleryfolder/profiles/default/viewlets.xml
collective/ptg/galleryfolder/profiles/default/types/.DS_Store
