Metadata-Version: 1.0
Name: collective.ptg.galleryfolder
Version: 0.3
Summary: galleryfolder gallery type for plonetruegallery
Home-page: https://github.com/medialog/collective.ptg.galleryfolder
Author: Espen Moe-Nilssen
Author-email: espen@medialog.no
License: GPL
Keywords: plonetruegaller gallery plone addon galleryfolder
Platform: UNKNOWN
Classifier: Framework :: Plone
Classifier: Programming Language :: Python
